odoo/addons/ddmrp_warning/README.rst
odoo/addons/ddmrp_warning/__init__.py
odoo/addons/ddmrp_warning/__manifest__.py
odoo/addons/ddmrp_warning/data/ddmrp_warning_definition_data.xml
odoo/addons/ddmrp_warning/data/ir_cron.xml
odoo/addons/ddmrp_warning/i18n/ddmrp_warning.pot
odoo/addons/ddmrp_warning/i18n/it.po
odoo/addons/ddmrp_warning/models/__init__.py
odoo/addons/ddmrp_warning/models/ddmrp_warning_definition.py
odoo/addons/ddmrp_warning/models/ddmrp_warning_item.py
odoo/addons/ddmrp_warning/models/stock_buffer.py
odoo/addons/ddmrp_warning/readme/CONTRIBUTORS.rst
odoo/addons/ddmrp_warning/readme/DESCRIPTION.rst
odoo/addons/ddmrp_warning/readme/USAGE.rst
odoo/addons/ddmrp_warning/security/ddmrp_warning_rules.xml
odoo/addons/ddmrp_warning/security/ir.model.access.csv
odoo/addons/ddmrp_warning/static/description/icon.png
odoo/addons/ddmrp_warning/static/description/index.html
odoo/addons/ddmrp_warning/tests/__init__.py
odoo/addons/ddmrp_warning/tests/test_ddmrp_warning.py
odoo/addons/ddmrp_warning/views/ddmrp_buffer_view.xml
odoo/addons/ddmrp_warning/views/ddmrp_warning_definition_views.xml
odoo/addons/ddmrp_warning/views/ddmrp_warning_item_views.xml
odoo13_addon_ddmrp_warning-13.0.1.5.1.dist-info/METADATA
odoo13_addon_ddmrp_warning-13.0.1.5.1.dist-info/WHEEL
odoo13_addon_ddmrp_warning-13.0.1.5.1.dist-info/top_level.txt
odoo13_addon_ddmrp_warning-13.0.1.5.1.dist-info/RECORD
